fatoora_einvoice_zatca_phase2/__init__.py
fatoora_einvoice_zatca_phase2/zatca_signing_service.py
fatoora_einvoice-1.1.0.dist-info/METADATA
fatoora_einvoice-1.1.0.dist-info/WHEEL
fatoora_einvoice-1.1.0.dist-info/top_level.txt
fatoora_einvoice-1.1.0.dist-info/RECORD
